wring/__init__.py
wring/_app.py
wring/_version.py
wring/csv.py
wring/omx.py
wring/py.typed
wring/tar_zst.py
wring-0.0.6.dist-info/METADATA
wring-0.0.6.dist-info/WHEEL
wring-0.0.6.dist-info/entry_points.txt
wring-0.0.6.dist-info/licenses/LICENSE
wring-0.0.6.dist-info/RECORD
