Metadata-Version: 2.3
Name: wring
Version: 0.0.6
Summary: A tool to compress multiple CSV data files into parquet
Project-URL: Documentation, https://jpn--.github.io/wring
Project-URL: Issues, https://github.com/jpn--/wring/issues
Project-URL: Source, https://github.com/jpn--/wring
Author: Jeff Newman
License-Expression: MIT
License-File: LICENSE
Classifier: Development Status :: 4 - Beta
Classifier: Programming Language :: Python
Classifier: Programming Language :: Python :: 3.10
Classifier: Programming Language :: Python :: Implementation :: CPython
Classifier: Programming Language :: Python :: Implementation :: PyPy
Requires-Python: >=3.10
Requires-Dist: pyarrow
Requires-Dist: rich
Requires-Dist: split-file-reader
Requires-Dist: typer
Requires-Dist: zstandard
Provides-Extra: docs
Requires-Dist: mkdocs-click; extra == 'docs'
Requires-Dist: mkdocs-git-revision-date-localized-plugin~=1.1.0; extra == 'docs'
Requires-Dist: mkdocs-material~=8.5.4; extra == 'docs'
Requires-Dist: mkdocs-typer; extra == 'docs'
Requires-Dist: mkdocstrings[python]~=0.19.0; extra == 'docs'
Requires-Dist: mkdocs~=1.4.0; extra == 'docs'
Provides-Extra: omx
Requires-Dist: pytables; extra == 'omx'
Provides-Extra: quality
Requires-Dist: black~=22.10.0; extra == 'quality'
Requires-Dist: pre-commit~=2.20.0; extra == 'quality'
Requires-Dist: ruff; extra == 'quality'
Provides-Extra: tests
Requires-Dist: pytest~=7.1.2; extra == 'tests'
Requires-Dist: tables; extra == 'tests'
